[
  {
    "name": "Application Start",
    "start": 1546499137136,
    "end": 1546499138351,
    "duration": 1215,
    "pid": 9452,
    "index": 0
  },
  {
    "name": "Load Plugin",
    "start": 1546499137143,
    "end": 1546499137172,
    "duration": 29,
    "pid": 9452,
    "index": 1
  },
  {
    "name": "Load Config",
    "start": 1546499137172,
    "end": 1546499137214,
    "duration": 42,
    "pid": 9452,
    "index": 2
  },
  {
    "name": "Require(0) config/config.default.js",
    "start": 1546499137173,
    "end": 1546499137174,
    "duration": 1,
    "pid": 9452,
    "index": 3
  },
  {
    "name": "Require(1) node_modules/egg-session/config/config.default.js",
    "start": 1546499137177,
    "end": 1546499137177,
    "duration": 0,
    "pid": 9452,
    "index": 4
  },
  {
    "name": "Require(2) node_modules/egg-security/config/config.default.js",
    "start": 1546499137178,
    "end": 1546499137179,
    "duration": 1,
    "pid": 9452,
    "index": 5
  },
  {
    "name": "Require(3) node_modules/egg-jsonp/config/config.default.js",
    "start": 1546499137180,
    "end": 1546499137181,
    "duration": 1,
    "pid": 9452,
    "index": 6
  },
  {
    "name": "Require(4) node_modules/egg-onerror/config/config.default.js",
    "start": 1546499137182,
    "end": 1546499137182,
    "duration": 0,
    "pid": 9452,
    "index": 7
  },
  {
    "name": "Require(5) node_modules/egg-i18n/config/config.default.js",
    "start": 1546499137183,
    "end": 1546499137184,
    "duration": 1,
    "pid": 9452,
    "index": 8
  },
  {
    "name": "Require(6) node_modules/egg-watcher/config/config.default.js",
    "start": 1546499137184,
    "end": 1546499137185,
    "duration": 1,
    "pid": 9452,
    "index": 9
  },
  {
    "name": "Require(7) node_modules/egg-schedule/config/config.default.js",
    "start": 1546499137186,
    "end": 1546499137187,
    "duration": 1,
    "pid": 9452,
    "index": 10
  },
  {
    "name": "Require(8) node_modules/egg-multipart/config/config.default.js",
    "start": 1546499137187,
    "end": 1546499137188,
    "duration": 1,
    "pid": 9452,
    "index": 11
  },
  {
    "name": "Require(9) node_modules/egg-development/config/config.default.js",
    "start": 1546499137189,
    "end": 1546499137190,
    "duration": 1,
    "pid": 9452,
    "index": 12
  },
  {
    "name": "Require(10) node_modules/egg-logrotator/config/config.default.js",
    "start": 1546499137191,
    "end": 1546499137191,
    "duration": 0,
    "pid": 9452,
    "index": 13
  },
  {
    "name": "Require(11) node_modules/egg-static/config/config.default.js",
    "start": 1546499137192,
    "end": 1546499137193,
    "duration": 1,
    "pid": 9452,
    "index": 14
  },
  {
    "name": "Require(12) node_modules/egg-view/config/config.default.js",
    "start": 1546499137194,
    "end": 1546499137194,
    "duration": 0,
    "pid": 9452,
    "index": 15
  },
  {
    "name": "Require(13) node_modules/egg-mysql/config/config.default.js",
    "start": 1546499137195,
    "end": 1546499137196,
    "duration": 1,
    "pid": 9452,
    "index": 16
  },
  {
    "name": "Require(14) node_modules/egg-cors/config/config.default.js",
    "start": 1546499137197,
    "end": 1546499137197,
    "duration": 0,
    "pid": 9452,
    "index": 17
  },
  {
    "name": "Require(15) node_modules/egg-validate/config/config.default.js",
    "start": 1546499137198,
    "end": 1546499137199,
    "duration": 1,
    "pid": 9452,
    "index": 18
  },
  {
    "name": "Require(16) node_modules/egg-redis/config/config.default.js",
    "start": 1546499137200,
    "end": 1546499137200,
    "duration": 0,
    "pid": 9452,
    "index": 19
  },
  {
    "name": "Require(17) node_modules/egg-jwt/config/config.default.js",
    "start": 1546499137201,
    "end": 1546499137202,
    "duration": 1,
    "pid": 9452,
    "index": 20
  },
  {
    "name": "Require(18) node_modules/egg/config/config.default.js",
    "start": 1546499137202,
    "end": 1546499137203,
    "duration": 1,
    "pid": 9452,
    "index": 21
  },
  {
    "name": "Require(19) config/config.default.js",
    "start": 1546499137206,
    "end": 1546499137206,
    "duration": 0,
    "pid": 9452,
    "index": 22
  },
  {
    "name": "Require(20) node_modules/egg-security/config/config.local.js",
    "start": 1546499137207,
    "end": 1546499137207,
    "duration": 0,
    "pid": 9452,
    "index": 23
  },
  {
    "name": "Require(21) node_modules/egg-watcher/config/config.local.js",
    "start": 1546499137209,
    "end": 1546499137209,
    "duration": 0,
    "pid": 9452,
    "index": 24
  },
  {
    "name": "Require(22) node_modules/egg-view/config/config.local.js",
    "start": 1546499137211,
    "end": 1546499137211,
    "duration": 0,
    "pid": 9452,
    "index": 25
  },
  {
    "name": "Require(23) node_modules/egg/config/config.local.js",
    "start": 1546499137213,
    "end": 1546499137213,
    "duration": 0,
    "pid": 9452,
    "index": 26
  },
  {
    "name": "Load extend/application.js",
    "start": 1546499137216,
    "end": 1546499137421,
    "duration": 205,
    "pid": 9452,
    "index": 27
  },
  {
    "name": "Require(24) node_modules/egg-session/app/extend/application.js",
    "start": 1546499137217,
    "end": 1546499137217,
    "duration": 0,
    "pid": 9452,
    "index": 28
  },
  {
    "name": "Require(25) node_modules/egg-security/app/extend/application.js",
    "start": 1546499137218,
    "end": 1546499137220,
    "duration": 2,
    "pid": 9452,
    "index": 29
  },
  {
    "name": "Require(26) node_modules/egg-jsonp/app/extend/application.js",
    "start": 1546499137221,
    "end": 1546499137223,
    "duration": 2,
    "pid": 9452,
    "index": 30
  },
  {
    "name": "Require(27) node_modules/egg-logrotator/app/extend/application.js",
    "start": 1546499137225,
    "end": 1546499137227,
    "duration": 2,
    "pid": 9452,
    "index": 31
  },
  {
    "name": "Require(28) node_modules/egg-view/app/extend/application.js",
    "start": 1546499137228,
    "end": 1546499137230,
    "duration": 2,
    "pid": 9452,
    "index": 32
  },
  {
    "name": "Require(29) node_modules/egg-jwt/app/extend/application.js",
    "start": 1546499137232,
    "end": 1546499137379,
    "duration": 147,
    "pid": 9452,
    "index": 33
  },
  {
    "name": "Load extend/request.js",
    "start": 1546499137421,
    "end": 1546499137453,
    "duration": 32,
    "pid": 9452,
    "index": 34
  },
  {
    "name": "Require(30) node_modules/egg/app/extend/request.js",
    "start": 1546499137427,
    "end": 1546499137447,
    "duration": 20,
    "pid": 9452,
    "index": 35
  },
  {
    "name": "Load extend/response.js",
    "start": 1546499137454,
    "end": 1546499137494,
    "duration": 40,
    "pid": 9452,
    "index": 36
  },
  {
    "name": "Require(31) node_modules/egg/app/extend/response.js",
    "start": 1546499137470,
    "end": 1546499137489,
    "duration": 19,
    "pid": 9452,
    "index": 37
  },
  {
    "name": "Load extend/context.js",
    "start": 1546499137494,
    "end": 1546499137614,
    "duration": 120,
    "pid": 9452,
    "index": 38
  },
  {
    "name": "Require(32) node_modules/egg-security/app/extend/context.js",
    "start": 1546499137495,
    "end": 1546499137526,
    "duration": 31,
    "pid": 9452,
    "index": 39
  },
  {
    "name": "Require(33) node_modules/egg-jsonp/app/extend/context.js",
    "start": 1546499137527,
    "end": 1546499137529,
    "duration": 2,
    "pid": 9452,
    "index": 40
  },
  {
    "name": "Require(34) node_modules/egg-i18n/app/extend/context.js",
    "start": 1546499137530,
    "end": 1546499137531,
    "duration": 1,
    "pid": 9452,
    "index": 41
  },
  {
    "name": "Require(35) node_modules/egg-multipart/app/extend/context.js",
    "start": 1546499137532,
    "end": 1546499137602,
    "duration": 70,
    "pid": 9452,
    "index": 42
  },
  {
    "name": "Require(36) node_modules/egg-view/app/extend/context.js",
    "start": 1546499137603,
    "end": 1546499137605,
    "duration": 2,
    "pid": 9452,
    "index": 43
  },
  {
    "name": "Require(37) node_modules/egg-validate/app/extend/context.js",
    "start": 1546499137606,
    "end": 1546499137607,
    "duration": 1,
    "pid": 9452,
    "index": 44
  },
  {
    "name": "Require(38) node_modules/egg/app/extend/context.js",
    "start": 1546499137608,
    "end": 1546499137610,
    "duration": 2,
    "pid": 9452,
    "index": 45
  },
  {
    "name": "Load extend/helper.js",
    "start": 1546499137615,
    "end": 1546499137655,
    "duration": 40,
    "pid": 9452,
    "index": 46
  },
  {
    "name": "Require(39) node_modules/egg-security/app/extend/helper.js",
    "start": 1546499137615,
    "end": 1546499137644,
    "duration": 29,
    "pid": 9452,
    "index": 47
  },
  {
    "name": "Require(40) node_modules/egg/app/extend/helper.js",
    "start": 1546499137651,
    "end": 1546499137651,
    "duration": 0,
    "pid": 9452,
    "index": 48
  },
  {
    "name": "Load app.js",
    "start": 1546499137656,
    "end": 1546499137768,
    "duration": 112,
    "pid": 9452,
    "index": 49
  },
  {
    "name": "Require(41) node_modules/egg-session/app.js",
    "start": 1546499137656,
    "end": 1546499137657,
    "duration": 1,
    "pid": 9452,
    "index": 50
  },
  {
    "name": "Require(42) node_modules/egg-security/app.js",
    "start": 1546499137658,
    "end": 1546499137661,
    "duration": 3,
    "pid": 9452,
    "index": 51
  },
  {
    "name": "Require(43) node_modules/egg-onerror/app.js",
    "start": 1546499137662,
    "end": 1546499137680,
    "duration": 18,
    "pid": 9452,
    "index": 52
  },
  {
    "name": "Require(44) node_modules/egg-i18n/app.js",
    "start": 1546499137681,
    "end": 1546499137705,
    "duration": 24,
    "pid": 9452,
    "index": 53
  },
  {
    "name": "Require(45) node_modules/egg-watcher/app.js",
    "start": 1546499137706,
    "end": 1546499137712,
    "duration": 6,
    "pid": 9452,
    "index": 54
  },
  {
    "name": "Require(46) node_modules/egg-schedule/app.js",
    "start": 1546499137713,
    "end": 1546499137715,
    "duration": 2,
    "pid": 9452,
    "index": 55
  },
  {
    "name": "Require(47) node_modules/egg-multipart/app.js",
    "start": 1546499137716,
    "end": 1546499137720,
    "duration": 4,
    "pid": 9452,
    "index": 56
  },
  {
    "name": "Require(48) node_modules/egg-development/app.js",
    "start": 1546499137721,
    "end": 1546499137721,
    "duration": 0,
    "pid": 9452,
    "index": 57
  },
  {
    "name": "Require(49) node_modules/egg-logrotator/app.js",
    "start": 1546499137722,
    "end": 1546499137723,
    "duration": 1,
    "pid": 9452,
    "index": 58
  },
  {
    "name": "Require(50) node_modules/egg-static/app.js",
    "start": 1546499137723,
    "end": 1546499137724,
    "duration": 1,
    "pid": 9452,
    "index": 59
  },
  {
    "name": "Require(51) node_modules/egg-mysql/app.js",
    "start": 1546499137725,
    "end": 1546499137758,
    "duration": 33,
    "pid": 9452,
    "index": 60
  },
  {
    "name": "Require(52) node_modules/egg-cors/app.js",
    "start": 1546499137759,
    "end": 1546499137759,
    "duration": 0,
    "pid": 9452,
    "index": 61
  },
  {
    "name": "Require(53) node_modules/egg-validate/app.js",
    "start": 1546499137760,
    "end": 1546499137763,
    "duration": 3,
    "pid": 9452,
    "index": 62
  },
  {
    "name": "Require(54) node_modules/egg-redis/app.js",
    "start": 1546499137764,
    "end": 1546499137766,
    "duration": 2,
    "pid": 9452,
    "index": 63
  },
  {
    "name": "Require(55) node_modules/egg-jwt/app.js",
    "start": 1546499137766,
    "end": 1546499137767,
    "duration": 1,
    "pid": 9452,
    "index": 64
  },
  {
    "name": "Before Start in node_modules/egg-watcher/lib/init.js:15:14",
    "start": 1546499137786,
    "end": 1546499138344,
    "duration": 558,
    "pid": 9452,
    "index": 65
  },
  {
    "name": "Before Start in node_modules/egg-mysql/lib/mysql.js:20:7",
    "start": 1546499138030,
    "end": 1546499138350,
    "duration": 320,
    "pid": 9452,
    "index": 66
  },
  {
    "name": "Load Service",
    "start": 1546499138031,
    "end": 1546499138038,
    "duration": 7,
    "pid": 9452,
    "index": 67
  },
  {
    "name": "Load \"service\" to Context",
    "start": 1546499138032,
    "end": 1546499138038,
    "duration": 6,
    "pid": 9452,
    "index": 68
  },
  {
    "name": "Load Middleware",
    "start": 1546499138038,
    "end": 1546499138283,
    "duration": 245,
    "pid": 9452,
    "index": 69
  },
  {
    "name": "Load \"middlewares\" to Application",
    "start": 1546499138039,
    "end": 1546499138258,
    "duration": 219,
    "pid": 9452,
    "index": 70
  },
  {
    "name": "Load Controller",
    "start": 1546499138283,
    "end": 1546499138289,
    "duration": 6,
    "pid": 9452,
    "index": 71
  },
  {
    "name": "Load \"controller\" to Application",
    "start": 1546499138283,
    "end": 1546499138289,
    "duration": 6,
    "pid": 9452,
    "index": 72
  },
  {
    "name": "Load Router",
    "start": 1546499138289,
    "end": 1546499138294,
    "duration": 5,
    "pid": 9452,
    "index": 73
  },
  {
    "name": "Require(56) app/router.js",
    "start": 1546499138289,
    "end": 1546499138290,
    "duration": 1,
    "pid": 9452,
    "index": 74
  },
  {
    "name": "Before Start in node_modules/egg-core/lib/egg.js:287:10",
    "start": 1546499138291,
    "end": 1546499138321,
    "duration": 30,
    "pid": 9452,
    "index": 75
  }
]