[
  {
    "name": "Application Start",
    "start": 1546499785805,
    "end": 1546499787186,
    "duration": 1381,
    "pid": 8024,
    "index": 0
  },
  {
    "name": "Load Plugin",
    "start": 1546499785812,
    "end": 1546499785847,
    "duration": 35,
    "pid": 8024,
    "index": 1
  },
  {
    "name": "Load Config",
    "start": 1546499785847,
    "end": 1546499785898,
    "duration": 51,
    "pid": 8024,
    "index": 2
  },
  {
    "name": "Require(0) config/config.default.js",
    "start": 1546499785848,
    "end": 1546499785849,
    "duration": 1,
    "pid": 8024,
    "index": 3
  },
  {
    "name": "Require(1) node_modules/egg-session/config/config.default.js",
    "start": 1546499785852,
    "end": 1546499785853,
    "duration": 1,
    "pid": 8024,
    "index": 4
  },
  {
    "name": "Require(2) node_modules/egg-security/config/config.default.js",
    "start": 1546499785853,
    "end": 1546499785854,
    "duration": 1,
    "pid": 8024,
    "index": 5
  },
  {
    "name": "Require(3) node_modules/egg-jsonp/config/config.default.js",
    "start": 1546499785856,
    "end": 1546499785857,
    "duration": 1,
    "pid": 8024,
    "index": 6
  },
  {
    "name": "Require(4) node_modules/egg-onerror/config/config.default.js",
    "start": 1546499785858,
    "end": 1546499785858,
    "duration": 0,
    "pid": 8024,
    "index": 7
  },
  {
    "name": "Require(5) node_modules/egg-i18n/config/config.default.js",
    "start": 1546499785859,
    "end": 1546499785860,
    "duration": 1,
    "pid": 8024,
    "index": 8
  },
  {
    "name": "Require(6) node_modules/egg-watcher/config/config.default.js",
    "start": 1546499785861,
    "end": 1546499785862,
    "duration": 1,
    "pid": 8024,
    "index": 9
  },
  {
    "name": "Require(7) node_modules/egg-schedule/config/config.default.js",
    "start": 1546499785862,
    "end": 1546499785863,
    "duration": 1,
    "pid": 8024,
    "index": 10
  },
  {
    "name": "Require(8) node_modules/egg-multipart/config/config.default.js",
    "start": 1546499785864,
    "end": 1546499785865,
    "duration": 1,
    "pid": 8024,
    "index": 11
  },
  {
    "name": "Require(9) node_modules/egg-development/config/config.default.js",
    "start": 1546499785866,
    "end": 1546499785867,
    "duration": 1,
    "pid": 8024,
    "index": 12
  },
  {
    "name": "Require(10) node_modules/egg-logrotator/config/config.default.js",
    "start": 1546499785867,
    "end": 1546499785868,
    "duration": 1,
    "pid": 8024,
    "index": 13
  },
  {
    "name": "Require(11) node_modules/egg-static/config/config.default.js",
    "start": 1546499785869,
    "end": 1546499785870,
    "duration": 1,
    "pid": 8024,
    "index": 14
  },
  {
    "name": "Require(12) node_modules/egg-view/config/config.default.js",
    "start": 1546499785871,
    "end": 1546499785872,
    "duration": 1,
    "pid": 8024,
    "index": 15
  },
  {
    "name": "Require(13) node_modules/egg-mysql/config/config.default.js",
    "start": 1546499785873,
    "end": 1546499785877,
    "duration": 4,
    "pid": 8024,
    "index": 16
  },
  {
    "name": "Require(14) node_modules/egg-cors/config/config.default.js",
    "start": 1546499785878,
    "end": 1546499785879,
    "duration": 1,
    "pid": 8024,
    "index": 17
  },
  {
    "name": "Require(15) node_modules/egg-validate/config/config.default.js",
    "start": 1546499785879,
    "end": 1546499785880,
    "duration": 1,
    "pid": 8024,
    "index": 18
  },
  {
    "name": "Require(16) node_modules/egg-redis/config/config.default.js",
    "start": 1546499785881,
    "end": 1546499785882,
    "duration": 1,
    "pid": 8024,
    "index": 19
  },
  {
    "name": "Require(17) node_modules/egg-jwt/config/config.default.js",
    "start": 1546499785882,
    "end": 1546499785883,
    "duration": 1,
    "pid": 8024,
    "index": 20
  },
  {
    "name": "Require(18) node_modules/egg/config/config.default.js",
    "start": 1546499785884,
    "end": 1546499785885,
    "duration": 1,
    "pid": 8024,
    "index": 21
  },
  {
    "name": "Require(19) config/config.default.js",
    "start": 1546499785888,
    "end": 1546499785889,
    "duration": 1,
    "pid": 8024,
    "index": 22
  },
  {
    "name": "Require(20) node_modules/egg-security/config/config.local.js",
    "start": 1546499785890,
    "end": 1546499785890,
    "duration": 0,
    "pid": 8024,
    "index": 23
  },
  {
    "name": "Require(21) node_modules/egg-watcher/config/config.local.js",
    "start": 1546499785892,
    "end": 1546499785892,
    "duration": 0,
    "pid": 8024,
    "index": 24
  },
  {
    "name": "Require(22) node_modules/egg-view/config/config.local.js",
    "start": 1546499785894,
    "end": 1546499785895,
    "duration": 1,
    "pid": 8024,
    "index": 25
  },
  {
    "name": "Require(23) node_modules/egg/config/config.local.js",
    "start": 1546499785897,
    "end": 1546499785898,
    "duration": 1,
    "pid": 8024,
    "index": 26
  },
  {
    "name": "Load extend/application.js",
    "start": 1546499785900,
    "end": 1546499786017,
    "duration": 117,
    "pid": 8024,
    "index": 27
  },
  {
    "name": "Require(24) node_modules/egg-session/app/extend/application.js",
    "start": 1546499785901,
    "end": 1546499785902,
    "duration": 1,
    "pid": 8024,
    "index": 28
  },
  {
    "name": "Require(25) node_modules/egg-security/app/extend/application.js",
    "start": 1546499785903,
    "end": 1546499785905,
    "duration": 2,
    "pid": 8024,
    "index": 29
  },
  {
    "name": "Require(26) node_modules/egg-jsonp/app/extend/application.js",
    "start": 1546499785906,
    "end": 1546499785918,
    "duration": 12,
    "pid": 8024,
    "index": 30
  },
  {
    "name": "Require(27) node_modules/egg-logrotator/app/extend/application.js",
    "start": 1546499785920,
    "end": 1546499785929,
    "duration": 9,
    "pid": 8024,
    "index": 31
  },
  {
    "name": "Require(28) node_modules/egg-view/app/extend/application.js",
    "start": 1546499785930,
    "end": 1546499785933,
    "duration": 3,
    "pid": 8024,
    "index": 32
  },
  {
    "name": "Require(29) node_modules/egg-jwt/app/extend/application.js",
    "start": 1546499785934,
    "end": 1546499786012,
    "duration": 78,
    "pid": 8024,
    "index": 33
  },
  {
    "name": "Load extend/request.js",
    "start": 1546499786017,
    "end": 1546499786028,
    "duration": 11,
    "pid": 8024,
    "index": 34
  },
  {
    "name": "Require(30) node_modules/egg/app/extend/request.js",
    "start": 1546499786021,
    "end": 1546499786024,
    "duration": 3,
    "pid": 8024,
    "index": 35
  },
  {
    "name": "Load extend/response.js",
    "start": 1546499786028,
    "end": 1546499786040,
    "duration": 12,
    "pid": 8024,
    "index": 36
  },
  {
    "name": "Require(31) node_modules/egg/app/extend/response.js",
    "start": 1546499786033,
    "end": 1546499786035,
    "duration": 2,
    "pid": 8024,
    "index": 37
  },
  {
    "name": "Load extend/context.js",
    "start": 1546499786040,
    "end": 1546499786200,
    "duration": 160,
    "pid": 8024,
    "index": 38
  },
  {
    "name": "Require(32) node_modules/egg-security/app/extend/context.js",
    "start": 1546499786046,
    "end": 1546499786084,
    "duration": 38,
    "pid": 8024,
    "index": 39
  },
  {
    "name": "Require(33) node_modules/egg-jsonp/app/extend/context.js",
    "start": 1546499786085,
    "end": 1546499786090,
    "duration": 5,
    "pid": 8024,
    "index": 40
  },
  {
    "name": "Require(34) node_modules/egg-i18n/app/extend/context.js",
    "start": 1546499786091,
    "end": 1546499786092,
    "duration": 1,
    "pid": 8024,
    "index": 41
  },
  {
    "name": "Require(35) node_modules/egg-multipart/app/extend/context.js",
    "start": 1546499786093,
    "end": 1546499786177,
    "duration": 84,
    "pid": 8024,
    "index": 42
  },
  {
    "name": "Require(36) node_modules/egg-view/app/extend/context.js",
    "start": 1546499786178,
    "end": 1546499786187,
    "duration": 9,
    "pid": 8024,
    "index": 43
  },
  {
    "name": "Require(37) node_modules/egg-validate/app/extend/context.js",
    "start": 1546499786188,
    "end": 1546499786190,
    "duration": 2,
    "pid": 8024,
    "index": 44
  },
  {
    "name": "Require(38) node_modules/egg/app/extend/context.js",
    "start": 1546499786191,
    "end": 1546499786196,
    "duration": 5,
    "pid": 8024,
    "index": 45
  },
  {
    "name": "Load extend/helper.js",
    "start": 1546499786201,
    "end": 1546499786246,
    "duration": 45,
    "pid": 8024,
    "index": 46
  },
  {
    "name": "Require(39) node_modules/egg-security/app/extend/helper.js",
    "start": 1546499786201,
    "end": 1546499786233,
    "duration": 32,
    "pid": 8024,
    "index": 47
  },
  {
    "name": "Require(40) node_modules/egg/app/extend/helper.js",
    "start": 1546499786239,
    "end": 1546499786240,
    "duration": 1,
    "pid": 8024,
    "index": 48
  },
  {
    "name": "Load app.js",
    "start": 1546499786246,
    "end": 1546499786574,
    "duration": 328,
    "pid": 8024,
    "index": 49
  },
  {
    "name": "Require(41) node_modules/egg-session/app.js",
    "start": 1546499786246,
    "end": 1546499786247,
    "duration": 1,
    "pid": 8024,
    "index": 50
  },
  {
    "name": "Require(42) node_modules/egg-security/app.js",
    "start": 1546499786248,
    "end": 1546499786253,
    "duration": 5,
    "pid": 8024,
    "index": 51
  },
  {
    "name": "Require(43) node_modules/egg-onerror/app.js",
    "start": 1546499786254,
    "end": 1546499786344,
    "duration": 90,
    "pid": 8024,
    "index": 52
  },
  {
    "name": "Require(44) node_modules/egg-i18n/app.js",
    "start": 1546499786346,
    "end": 1546499786376,
    "duration": 30,
    "pid": 8024,
    "index": 53
  },
  {
    "name": "Require(45) node_modules/egg-watcher/app.js",
    "start": 1546499786376,
    "end": 1546499786385,
    "duration": 9,
    "pid": 8024,
    "index": 54
  },
  {
    "name": "Require(46) node_modules/egg-schedule/app.js",
    "start": 1546499786385,
    "end": 1546499786391,
    "duration": 6,
    "pid": 8024,
    "index": 55
  },
  {
    "name": "Require(47) node_modules/egg-multipart/app.js",
    "start": 1546499786391,
    "end": 1546499786398,
    "duration": 7,
    "pid": 8024,
    "index": 56
  },
  {
    "name": "Require(48) node_modules/egg-development/app.js",
    "start": 1546499786398,
    "end": 1546499786399,
    "duration": 1,
    "pid": 8024,
    "index": 57
  },
  {
    "name": "Require(49) node_modules/egg-logrotator/app.js",
    "start": 1546499786400,
    "end": 1546499786401,
    "duration": 1,
    "pid": 8024,
    "index": 58
  },
  {
    "name": "Require(50) node_modules/egg-static/app.js",
    "start": 1546499786401,
    "end": 1546499786402,
    "duration": 1,
    "pid": 8024,
    "index": 59
  },
  {
    "name": "Require(51) node_modules/egg-mysql/app.js",
    "start": 1546499786403,
    "end": 1546499786516,
    "duration": 113,
    "pid": 8024,
    "index": 60
  },
  {
    "name": "Require(52) node_modules/egg-cors/app.js",
    "start": 1546499786519,
    "end": 1546499786554,
    "duration": 35,
    "pid": 8024,
    "index": 61
  },
  {
    "name": "Require(53) node_modules/egg-validate/app.js",
    "start": 1546499786556,
    "end": 1546499786563,
    "duration": 7,
    "pid": 8024,
    "index": 62
  },
  {
    "name": "Require(54) node_modules/egg-redis/app.js",
    "start": 1546499786564,
    "end": 1546499786568,
    "duration": 4,
    "pid": 8024,
    "index": 63
  },
  {
    "name": "Require(55) node_modules/egg-jwt/app.js",
    "start": 1546499786569,
    "end": 1546499786571,
    "duration": 2,
    "pid": 8024,
    "index": 64
  },
  {
    "name": "Before Start in node_modules/egg-watcher/lib/init.js:15:14",
    "start": 1546499786608,
    "end": 1546499787180,
    "duration": 572,
    "pid": 8024,
    "index": 65
  },
  {
    "name": "Before Start in node_modules/egg-mysql/lib/mysql.js:20:7",
    "start": 1546499786857,
    "end": 1546499787185,
    "duration": 328,
    "pid": 8024,
    "index": 66
  },
  {
    "name": "Load Service",
    "start": 1546499786858,
    "end": 1546499786866,
    "duration": 8,
    "pid": 8024,
    "index": 67
  },
  {
    "name": "Load \"service\" to Context",
    "start": 1546499786858,
    "end": 1546499786866,
    "duration": 8,
    "pid": 8024,
    "index": 68
  },
  {
    "name": "Load Middleware",
    "start": 1546499786867,
    "end": 1546499787091,
    "duration": 224,
    "pid": 8024,
    "index": 69
  },
  {
    "name": "Load \"middlewares\" to Application",
    "start": 1546499786867,
    "end": 1546499787068,
    "duration": 201,
    "pid": 8024,
    "index": 70
  },
  {
    "name": "Load Controller",
    "start": 1546499787091,
    "end": 1546499787097,
    "duration": 6,
    "pid": 8024,
    "index": 71
  },
  {
    "name": "Load \"controller\" to Application",
    "start": 1546499787091,
    "end": 1546499787097,
    "duration": 6,
    "pid": 8024,
    "index": 72
  },
  {
    "name": "Load Router",
    "start": 1546499787097,
    "end": 1546499787102,
    "duration": 5,
    "pid": 8024,
    "index": 73
  },
  {
    "name": "Require(56) app/router.js",
    "start": 1546499787098,
    "end": 1546499787098,
    "duration": 0,
    "pid": 8024,
    "index": 74
  },
  {
    "name": "Before Start in node_modules/egg-core/lib/egg.js:287:10",
    "start": 1546499787099,
    "end": 1546499787127,
    "duration": 28,
    "pid": 8024,
    "index": 75
  }
]